html_generators/README.md
html_generators/RELEASE_NOTES.md
html_generators/VERSION
html_generators/__init__.py
html_generators/__init__.pyc
html_generators/_base.py
html_generators/_comment.py
html_generators/_document.py
html_generators/_element.py
html_generators/_format.py
html_generators/_fragment.py
html_generators/_join.py
html_generators/_mark_safe.py
html_generators/_template.py
html_generators/_utils.py
html_generators/django.py
html_generators/py.typed
html_generators/__pycache__/__init__.cpython-36.pyc
html_generators/__pycache__/_base.cpython-36.pyc
html_generators/__pycache__/_comment.cpython-36.pyc
html_generators/__pycache__/_document.cpython-36.pyc
html_generators/__pycache__/_element.cpython-36.pyc
html_generators/__pycache__/_format.cpython-36.pyc
html_generators/__pycache__/_fragment.cpython-36.pyc
html_generators/__pycache__/_join.cpython-36.pyc
html_generators/__pycache__/_mark_safe.cpython-36.pyc
html_generators/__pycache__/_standard_elements.cpython-36.pyc
html_generators/__pycache__/_template.cpython-36.pyc
html_generators/__pycache__/_utils.cpython-36.pyc
html_generators/__pycache__/base.cpython-36.pyc
html_generators/__pycache__/comment.cpython-36.pyc
html_generators/__pycache__/django.cpython-36.pyc
html_generators/__pycache__/document.cpython-36.pyc
html_generators/__pycache__/elements.cpython-36.pyc
html_generators/__pycache__/fragment.cpython-36.pyc
html_generators/__pycache__/join.cpython-36.pyc
html_generators/__pycache__/mark_safe.cpython-36.pyc
html_generators/__pycache__/utils.cpython-36.pyc
html_generators-2.8.0.dist-info/LICENSE
html_generators-2.8.0.dist-info/METADATA
html_generators-2.8.0.dist-info/WHEEL
html_generators-2.8.0.dist-info/top_level.txt
html_generators-2.8.0.dist-info/RECORD
