Metadata-Version: 2.1
Name: html-generators
Version: 2.8.0
Summary: Functional, streaming approach to HTML generation
Home-page: https://github.com/quadrant-newmedia/html_generators
Author: Alex Fischer
Author-email: alex@quadrant.net
License: UNKNOWN
Platform: UNKNOWN
Classifier: Programming Language :: Python :: 3
Classifier: License :: OSI Approved :: MIT License
Classifier: Operating System :: OS Independent
Requires-Python: >=3.6
Requires-Dist: typing-extensions (<5,>=4.0)
